{
  "type": "FeatureCollection",
  "features": [
    {
      "type": "Feature",
      "geometry": {
        "type": "Polygon",
        "coordinates": [
          [
            [
              115.6,
              -8.80641,
              0
            ],
            [
              115.6,
              -8.97641,
              0
            ],
            [
              115.15,
              -9.01016,
              0
            ],
            [
              115.15,
              -8.84633,
              0
            ],
            [
              115.151,
              -8.84624,
              0
            ],
            [
              115.154,
              -8.84623,
              0
            ],
            [
              115.161,
              -8.84719,
              0
            ],
            [
              115.164,
              -8.84778,
              0
            ],
            [
              115.167,
              -8.84788,
              0
            ],
            [
              115.17,
              -8.84742,
              0
            ],
            [
              115.177,
              -8.84626,
              0
            ],
            [
              115.183,
              -8.84441,
              0
            ],
            [
              115.187,
              -8.8424,
              0
            ],
            [
              115.191,
              -8.84118,
              0
            ],
            [
              115.194,
              -8.84084,
              0
            ],
            [
              115.197,
              -8.83985,
              0
            ],
            [
              115.201,
              -8.83806,
              0
            ],
            [
              115.204,
              -8.8365,
              0
            ],
            [
              115.207,
              -8.83541,
              0
            ],
            [
              115.211,
              -8.83351,
              0
            ],
            [
              115.215,
              -8.83148,
              0
            ],
            [
              115.216,
              -8.83021,
              0
            ],
            [
              115.219,
              -8.82705,
              0
            ],
            [
              115.22,
              -8.82331,
              0
            ],
            [
              115.223,
              -8.81869,
              0
            ],
            [
              115.224,
              -8.8149,
              0
            ],
            [
              115.226,
              -8.81138,
              0
            ],
            [
              115.228,
              -8.80965,
              0
            ],
            [
              115.229,
              -8.80666,
              0
            ],
            [
              115.23,
              -8.80465,
              0
            ],
            [
              115.233,
              -8.80245,
              0
            ],
            [
              115.235,
              -8.80015,
              0
            ],
            [
              115.237,
              -8.80383,
              0
            ],
            [
              115.239,
              -8.80227,
              0
            ],
            [
              115.238,
              -8.80003,
              0
            ],
            [
              115.235,
              -8.80015,
              0
            ],
            [
              115.234,
              -8.79785,
              0
            ],
            [
              115.232,
              -8.79485,
              0
            ],
            [
              115.23,
              -8.7918,
              0
            ],
            [
              115.229,
              -8.78622,
              0
            ],
            [
              115.226,
              -8.78428,
              0
            ],
            [
              115.225,
              -8.78237,
              0
            ],
            [
              115.224,
              -8.78031,
              0
            ],
            [
              115.223,
              -8.77478,
              0
            ],
            [
              115.222,
              -8.76995,
              0
            ],
            [
              115.221,
              -8.76483,
              0
            ],
            [
              115.222,
              -8.76137,
              0
            ],
            [
              115.221,
              -8.7593,
              0
            ],
            [
              115.221,
              -8.75649,
              0
            ],
            [
              115.221,
              -8.75389,
              0
            ],
            [
              115.22,
              -8.75136,
              0
            ],
            [
              115.217,
              -8.75102,
              0
            ],
            [
              115.215,
              -8.75229,
              0
            ],
            [
              115.215,
              -8.75493,
              0
            ],
            [
              115.216,
              -8.75695,
              0
            ],
            [
              115.214,
              -8.75925,
              0
            ],
            [
              115.215,
              -8.76127,
              0
            ],
            [
              115.214,
              -8.76369,
              0
            ],
            [
              115.215,
              -8.76743,
              0
            ],
            [
              115.216,
              -8.7695,
              0
            ],
            [
              115.214,
              -8.77209,
              0
            ],
            [
              115.212,
              -8.77399,
              0
            ],
            [
              115.213,
              -8.77669,
              0
            ],
            [
              115.213,
              -8.77952,
              0
            ],
            [
              115.216,
              -8.78377,
              0
            ],
            [
              115.213,
              -8.7855,
              0
            ],
            [
              115.211,
              -8.78538,
              0
            ],
            [
              115.207,
              -8.78419,
              0
            ],
            [
              115.204,
              -8.78217,
              0
            ],
            [
              115.201,
              -8.78017,
              0
            ],
            [
              115.197,
              -8.77965,
              0
            ],
            [
              115.195,
              -8.77878,
              0
            ],
            [
              115.194,
              -8.77683,
              0
            ],
            [
              115.192,
              -8.77212,
              0
            ],
            [
              115.191,
              -8.76929,
              0
            ],
            [
              115.189,
              -8.76556,
              0
            ],
            [
              115.187,
              -8.76235,
              0
            ],
            [
              115.184,
              -8.76182,
              0
            ],
            [
              115.181,
              -8.7616,
              0
            ],
            [
              115.18,
              -8.75976,
              0
            ],
            [
              115.18,
              -8.75648,
              0
            ],
            [
              115.181,
              -8.75267,
              0
            ],
            [
              115.182,
              -8.74904,
              0
            ],
            [
              115.182,
              -8.74582,
              0
            ],
            [
              115.182,
              -8.74238,
              0
            ],
            [
              115.184,
              -8.74064,
              0
            ],
            [
              115.185,
              -8.73799,
              0
            ],
            [
              115.187,
              -8.73679,
              0
            ],
            [
              115.19,
              -8.73597,
              0
            ],
            [
              115.192,
              -8.73519,
              0
            ],
            [
              115.195,
              -8.73246,
              0
            ],
            [
              115.196,
              -8.73137,
              0
            ],
            [
              115.199,
              -8.72975,
              0
            ],
            [
              115.201,
              -8.72781,
              0
            ],
            [
              115.203,
              -8.72629,
              0
            ],
            [
              115.206,
              -8.72668,
              0
            ],
            [
              115.208,
              -8.72708,
              0
            ],
            [
              115.21,
              -8.72836,
              0
            ],
            [
              115.212,
              -8.72715,
              0
            ],
            [
              115.214,
              -8.72529,
              0
            ],
            [
              115.217,
              -8.72489,
              0
            ],
            [
              115.221,
              -8.72384,
              0
            ],
            [
              115.224,
              -8.7205,
              0
            ],
            [
              115.226,
              -8.7178,
              0
            ],
            [
              115.229,
              -8.71716,
              0
            ],
            [
              115.231,
              -8.71633,
              0
            ],
            [
              115.234,
              -8.71572,
              0
            ],
            [
              115.237,
              -8.71473,
              0
            ],
            [
              115.239,
              -8.71208,
              0
            ],
            [
              115.242,
              -8.71076,
              0
            ],
            [
              115.244,
              -8.7096,
              0
            ],
            [
              115.246,
              -8.70897,
              0
            ],
            [
              115.25,
              -8.70907,
              0
            ],
            [
              115.254,
              -8.70867,
              0
            ],
            [
              115.258,
              -8.7067,
              0
            ],
            [
              115.26,
              -8.704,
              0
            ],
            [
              115.262,
              -8.70048,
              0
            ],
            [
              115.264,
              -8.6972,
              0
            ],
            [
              115.264,
              -8.69381,
              0
            ],
            [
              115.264,
              -8.69145,
              0
            ],
            [
              115.264,
              -8.68719,
              0
            ],
            [
              115.264,
              -8.68483,
              0
            ],
            [
              115.263,
              -8.68218,
              0
            ],
            [
              115.263,
              -8.67885,
              0
            ],
            [
              115.263,
              -8.67596,
              0
            ],
            [
              115.262,
              -8.67286,
              0
            ],
            [
              115.26,
              -8.669,
              0
            ],
            [
              115.259,
              -8.6667,
              0
            ],
            [
              115.26,
              -8.66371,
              0
            ],
            [
              115.262,
              -8.66058,
              0
            ],
            [
              115.263,
              -8.65864,
              0
            ],
            [
              115.264,
              -8.65616,
              0
            ],
            [
              115.263,
              -8.65432,
              0
            ],
            [
              115.264,
              -8.65253,
              0
            ],
            [
              115.267,
              -8.65265,
              0
            ],
            [
              115.269,
              -8.65184,
              0
            ],
            [
              115.272,
              -8.65006,
              0
            ],
            [
              115.272,
              -8.64799,
              0
            ],
            [
              115.276,
              -8.64745,
              0
            ],
            [
              115.28,
              -8.64434,
              0
            ],
            [
              115.284,
              -8.641,
              0
            ],
            [
              115.286,
              -8.63939,
              0
            ],
            [
              115.289,
              -8.63587,
              0
            ],
            [
              115.291,
              -8.63426,
              0
            ],
            [
              115.296,
              -8.63005,
              0
            ],
            [
              115.299,
              -8.62654,
              0
            ],
            [
              115.3,
              -8.62377,
              0
            ],
            [
              115.302,
              -8.62083,
              0
            ],
            [
              115.304,
              -8.61882,
              0
            ],
            [
              115.308,
              -8.61696,
              0
            ],
            [
              115.312,
              -8.61552,
              0
            ],
            [
              115.315,
              -8.61472,
              0
            ],
            [
              115.318,
              -8.61373,
              0
            ],
            [
              115.32,
              -8.61189,
              0
            ],
            [
              115.322,
              -8.60795,
              0
            ],
            [
              115.323,
              -8.60573,
              0
            ],
            [
              115.326,
              -8.60235,
              0
            ],
            [
              115.331,
              -8.59967,
              0
            ],
            [
              115.333,
              -8.59846,
              0
            ],
            [
              115.334,
              -8.59719,
              0
            ],
            [
              115.338,
              -8.59523,
              0
            ],
            [
              115.34,
              -8.59402,
              0
            ],
            [
              115.342,
              -8.59304,
              0
            ],
            [
              115.346,
              -8.59065,
              0
            ],
            [
              115.348,
              -8.58734,
              0
            ],
            [
              115.351,
              -8.58394,
              0
            ],
            [
              115.352,
              -8.58226,
              0
            ],
            [
              115.354,
              -8.58093,
              0
            ],
            [
              115.358,
              -8.57884,
              0
            ],
            [
              115.361,
              -8.57765,
              0
            ],
            [
              115.363,
              -8.5773,
              0
            ],
            [
              115.366,
              -8.57724,
              0
            ],
            [
              115.37,
              -8.5766,
              0
            ],
            [
              115.373,
              -8.57648,
              0
            ],
            [
              115.376,
              -8.57378,
              0
            ],
            [
              115.379,
              -8.57498,
              0
            ],
            [
              115.382,
              -8.57532,
              0
            ],
            [
              115.386,
              -8.57495,
              0
            ],
            [
              115.388,
              -8.57463,
              0
            ],
            [
              115.392,
              -8.57445,
              0
            ],
            [
              115.395,
              -8.57456,
              0
            ],
            [
              115.399,
              -8.57495,
              0
            ],
            [
              115.402,
              -8.57452,
              0
            ],
            [
              115.406,
              -8.57414,
              0
            ],
            [
              115.413,
              -8.57303,
              0
            ],
            [
              115.42,
              -8.5717,
              0
            ],
            [
              115.426,
              -8.57118,
              0
            ],
            [
              115.429,
              -8.57044,
              0
            ],
            [
              115.433,
              -8.57001,
              0
            ],
            [
              115.436,
              -8.56983,
              0
            ],
            [
              115.44,
              -8.56943,
              0
            ],
            [
              115.444,
              -8.56833,
              0
            ],
            [
              115.448,
              -8.56588,
              0
            ],
            [
              115.45,
              -8.5643,
              0
            ],
            [
              115.451,
              -8.56205,
              0
            ],
            [
              115.454,
              -8.56026,
              0
            ],
            [
              115.456,
              -8.55836,
              0
            ],
            [
              115.458,
              -8.55617,
              0
            ],
            [
              115.461,
              -8.55358,
              0
            ],
            [
              115.464,
              -8.55231,
              0
            ],
            [
              115.467,
              -8.55098,
              0
            ],
            [
              115.471,
              -8.55018,
              0
            ],
            [
              115.477,
              -8.54942,
              0
            ],
            [
              115.48,
              -8.54918,
              0
            ],
            [
              115.484,
              -8.54894,
              0
            ],
            [
              115.486,
              -8.5486,
              0
            ],
            [
              115.492,
              -8.54778,
              0
            ],
            [
              115.496,
              -8.54749,
              0
            ],
            [
              115.5,
              -8.54662,
              0
            ],
            [
              115.505,
              -8.54535,
              0
            ],
            [
              115.51,
              -8.54199,
              0
            ],
            [
              115.514,
              -8.54026,
              0
            ],
            [
              115.515,
              -8.5364,
              0
            ],
            [
              115.512,
              -8.53537,
              0
            ],
            [
              115.511,
              -8.53306,
              0
            ],
            [
              115.515,
              -8.53127,
              0
            ],
            [
              115.517,
              -8.53201,
              0
            ],
            [
              115.519,
              -8.53368,
              0
            ],
            [
              115.521,
              -8.53327,
              0
            ],
            [
              115.52,
              -8.53045,
              0
            ],
            [
              115.519,
              -8.52803,
              0
            ],
            [
              115.516,
              -8.52505,
              0
            ],
            [
              115.515,
              -8.52292,
              0
            ],
            [
              115.514,
              -8.51987,
              0
            ],
            [
              115.512,
              -8.51659,
              0
            ],
            [
              115.513,
              -8.51248,
              0
            ],
            [
              115.515,
              -8.51023,
              0
            ],
            [
              115.517,
              -8.50817,
              0
            ],
            [
              115.52,
              -8.50608,
              0
            ],
            [
              115.526,
              -8.50377,
              0
            ],
            [
              115.53,
              -8.5024,
              0
            ],
            [
              115.535,
              -8.50052,
              0
            ],
            [
              115.539,
              -8.49942,
              0
            ],
            [
              115.543,
              -8.49959,
              0
            ],
            [
              115.545,
              -8.50054,
              0
            ],
            [
              115.553,
              -8.50395,
              0
            ],
            [
              115.559,
              -8.50416,
              0
            ],
            [
              115.563,
              -8.50584,
              0
            ],
            [
              115.566,
              -8.50742,
              0
            ],
            [
              115.568,
              -8.50829,
              0
            ],
            [
              115.574,
              -8.51231,
              0
            ],
            [
              115.577,
              -8.51408,
              0
            ],
            [
              115.584,
              -8.51602,
              0
            ],
            [
              115.589,
              -8.51504,
              0
            ],
            [
              115.595,
              -8.51209,
              0
            ],
            [
              115.6,
              -8.50933,
              0
            ],
            [
              115.6,
              -8.6,
              0
            ],
            [
              115.6,
              -8.7234,
              0
            ],
            [
              115.599,
              -8.7227,
              0
            ],
            [
              115.597,
              -8.71959,
              0
            ],
            [
              115.596,
              -8.71649,
              0
            ],
            [
              115.595,
              -8.71355,
              0
            ],
            [
              115.592,
              -8.71085,
              0
            ],
            [
              115.59,
              -8.70902,
              0
            ],
            [
              115.589,
              -8.70648,
              0
            ],
            [
              115.587,
              -8.70482,
              0
            ],
            [
              115.586,
              -8.70332,
              0
            ],
            [
              115.585,
              -8.70106,
              0
            ],
            [
              115.585,
              -8.6986,
              0
            ],
            [
              115.585,
              -8.69296,
              0
            ],
            [
              115.584,
              -8.68968,
              0
            ],
            [
              115.582,
              -8.68634,
              0
            ],
            [
              115.573,
              -8.67685,
              0
            ],
            [
              115.566,
              -8.671,
              0
            ],
            [
              115.559,
              -8.67113,
              0
            ],
            [
              115.552,
              -8.67293,
              0
            ],
            [
              115.546,
              -8.67622,
              0
            ],
            [
              115.541,
              -8.6779,
              0
            ],
            [
              115.536,
              -8.67846,
              0
            ],
            [
              115.534,
              -8.67878,
              0
            ],
            [
              115.531,
              -8.67891,
              0
            ],
            [
              115.527,
              -8.67857,
              0
            ],
            [
              115.523,
              -8.67841,
              0
            ],
            [
              115.52,
              -8.67813,
              0
            ],
            [
              115.517,
              -8.67681,
              0
            ],
            [
              115.514,
              -8.67543,
              0
            ],
            [
              115.505,
              -8.67176,
              0
            ],
            [
              115.5,
              -8.67137,
              0
            ],
            [
              115.497,
              -8.67095,
              0
            ],
            [
              115.493,
              -8.67082,
              0
            ],
            [
              115.491,
              -8.67142,
              0
            ],
            [
              115.488,
              -8.67376,
              0
            ],
            [
              115.487,
              -8.67647,
              0
            ],
            [
              115.486,
              -8.67883,
              0
            ],
            [
              115.485,
              -8.68052,
              0
            ],
            [
              115.483,
              -8.68146,
              0
            ],
            [
              115.481,
              -8.68206,
              0
            ],
            [
              115.476,
              -8.68464,
              0
            ],
            [
              115.474,
              -8.68662,
              0
            ],
            [
              115.472,
              -8.68876,
              0
            ],
            [
              115.471,
              -8.69081,
              0
            ],
            [
              115.469,
              -8.69364,
              0
            ],
            [
              115.467,
              -8.69728,
              0
            ],
            [
              115.465,
              -8.69936,
              0
            ],
            [
              115.464,
              -8.70117,
              0
            ],
            [
              115.462,
              -8.70257,
              0
            ],
            [
              115.459,
              -8.70484,
              0
            ],
            [
              115.456,
              -8.70839,
              0
            ],
            [
              115.457,
              -8.71176,
              0
            ],
            [
              115.457,
              -8.71372,
              0
            ],
            [
              115.456,
              -8.71539,
              0
            ],
            [
              115.452,
              -8.71665,
              0
            ],
            [
              115.449,
              -8.71789,
              0
            ],
            [
              115.447,
              -8.71964,
              0
            ],
            [
              115.445,
              -8.72219,
              0
            ],
            [
              115.446,
              -8.72476,
              0
            ],
            [
              115.448,
              -8.72497,
              0
            ],
            [
              115.45,
              -8.72604,
              0
            ],
            [
              115.449,
              -8.72762,
              0
            ],
            [
              115.446,
              -8.72856,
              0
            ],
            [
              115.446,
              -8.73161,
              0
            ],
            [
              115.449,
              -8.73152,
              0
            ],
            [
              115.451,
              -8.73311,
              0
            ],
            [
              115.454,
              -8.73353,
              0
            ],
            [
              115.453,
              -8.73723,
              0
            ],
            [
              115.452,
              -8.73953,
              0
            ],
            [
              115.449,
              -8.74209,
              0
            ],
            [
              115.45,
              -8.74491,
              0
            ],
            [
              115.453,
              -8.74683,
              0
            ],
            [
              115.456,
              -8.74501,
              0
            ],
            [
              115.459,
              -8.7444,
              0
            ],
            [
              115.462,
              -8.74522,
              0
            ],
            [
              115.465,
              -8.74703,
              0
            ],
            [
              115.468,
              -8.74769,
              0
            ],
            [
              115.47,
              -8.74865,
              0
            ],
            [
              115.47,
              -8.75095,
              0
            ],
            [
              115.473,
              -8.74999,
              0
            ],
            [
              115.477,
              -8.75214,
              0
            ],
            [
              115.479,
              -8.75362,
              0
            ],
            [
              115.479,
              -8.75585,
              0
            ],
            [
              115.483,
              -8.75713,
              0
            ],
            [
              115.484,
              -8.75878,
              0
            ],
            [
              115.484,
              -8.76229,
              0
            ],
            [
              115.484,
              -8.76488,
              0
            ],
            [
              115.485,
              -8.76705,
              0
            ],
            [
              115.488,
              -8.76777,
              0
            ],
            [
              115.49,
              -8.76895,
              0
            ],
            [
              115.493,
              -8.76886,
              0
            ],
            [
              115.496,
              -8.76998,
              0
            ],
            [
              115.498,
              -8.7718,
              0
            ],
            [
              115.5,
              -8.77234,
              0
            ],
            [
              115.505,
              -8.77302,
              0
            ],
            [
              115.515,
              -8.77592,
              0
            ],
            [
              115.517,
              -8.77789,
              0
            ],
            [
              115.52,
              -8.78088,
              0
            ],
            [
              115.522,
              -8.78237,
              0
            ],
            [
              115.525,
              -8.78594,
              0
            ],
            [
              115.524,
              -8.79019,
              0
            ],
            [
              115.526,
              -8.79152,
              0
            ],
            [
              115.529,
              -8.79226,
              0
            ],
            [
              115.53,
              -8.79514,
              0
            ],
            [
              115.531,
              -8.79808,
              0
            ],
            [
              115.534,
              -8.79732,
              0
            ],
            [
              115.538,
              -8.79495,
              0
            ],
            [
              115.542,
              -8.79609,
              0
            ],
            [
              115.544,
              -8.79673,
              0
            ],
            [
              115.55,
              -8.79826,
              0
            ],
            [
              115.553,
              -8.79992,
              0
            ],
            [
              115.561,
              -8.80221,
              0
            ],
            [
              115.564,
              -8.80382,
              0
            ],
            [
              115.567,
              -8.80623,
              0
            ],
            [
              115.57,
              -8.80892,
              0
            ],
            [
              115.573,
              -8.8099,
              0
            ],
            [
              115.58,
              -8.81132,
              0
            ],
            [
              115.582,
              -8.81368,
              0
            ],
            [
              115.586,
              -8.81672,
              0
            ],
            [
              115.588,
              -8.81816,
              0
            ],
            [
              115.59,
              -8.817,
              0
            ],
            [
              115.592,
              -8.81412,
              0
            ],
            [
              115.594,
              -8.81158,
              0
            ],
            [
              115.595,
              -8.80939,
              0
            ],
            [
              115.598,
              -8.80829,
              0
            ],
            [
              115.6,
              -8.80638,
              0
            ],
            [
              115.6,
              -8.80641,
              0
            ]
          ],
          [
            [
              115.222,
              -8.74151,
              0
            ],
            [
              115.225,
              -8.74025,
              0
            ],
            [
              115.227,
              -8.73822,
              0
            ],
            [
              115.228,
              -8.73684,
              0
            ],
            [
              115.231,
              -8.73512,
              0
            ],
            [
              115.232,
              -8.73287,
              0
            ],
            [
              115.233,
              -8.73062,
              0
            ],
            [
              115.236,
              -8.72596,
              0
            ],
            [
              115.236,
              -8.72203,
              0
            ],
            [
              115.231,
              -8.72515,
              0
            ],
            [
              115.23,
              -8.72303,
              0
            ],
            [
              115.228,
              -8.72257,
              0
            ],
            [
              115.227,
              -8.72465,
              0
            ],
            [
              115.226,
              -8.72884,
              0
            ],
            [
              115.224,
              -8.73109,
              0
            ],
            [
              115.223,
              -8.73363,
              0
            ],
            [
              115.222,
              -8.736,
              0
            ],
            [
              115.222,
              -8.73903,
              0
            ],
            [
              115.222,
              -8.74151,
              0
            ]
          ],
          [
            [
              115.442,
              -8.71032,
              0
            ],
            [
              115.443,
              -8.70837,
              0
            ],
            [
              115.445,
              -8.70796,
              0
            ],
            [
              115.447,
              -8.70669,
              0
            ],
            [
              115.448,
              -8.70456,
              0
            ],
            [
              115.449,
              -8.70294,
              0
            ],
            [
              115.452,
              -8.7018,
              0
            ],
            [
              115.454,
              -8.70035,
              0
            ],
            [
              115.457,
              -8.69799,
              0
            ],
            [
              115.459,
              -8.69476,
              0
            ],
            [
              115.461,
              -8.68964,
              0
            ],
            [
              115.462,
              -8.68774,
              0
            ],
            [
              115.462,
              -8.68469,
              0
            ],
            [
              115.459,
              -8.68544,
              0
            ],
            [
              115.456,
              -8.68768,
              0
            ],
            [
              115.454,
              -8.69051,
              0
            ],
            [
              115.451,
              -8.69236,
              0
            ],
            [
              115.448,
              -8.69323,
              0
            ],
            [
              115.447,
              -8.69455,
              0
            ],
            [
              115.444,
              -8.69651,
              0
            ],
            [
              115.441,
              -8.69812,
              0
            ],
            [
              115.438,
              -8.70008,
              0
            ],
            [
              115.437,
              -8.70331,
              0
            ],
            [
              115.436,
              -8.70573,
              0
            ],
            [
              115.437,
              -8.70769,
              0
            ],
            [
              115.438,
              -8.71021,
              0
            ],
            [
              115.442,
              -8.71032,
              0
            ]
          ],
          [
            [
              115.454,
              -8.66239,
              0
            ],
            [
              115.452,
              -8.66145,
              0
            ],
            [
              115.45,
              -8.66185,
              0
            ],
            [
              115.447,
              -8.66307,
              0
            ],
            [
              115.445,
              -8.66531,
              0
            ],
            [
              115.444,
              -8.66854,
              0
            ],
            [
              115.443,
              -8.6728,
              0
            ],
            [
              115.443,
              -8.67694,
              0
            ],
            [
              115.44,
              -8.67746,
              0
            ],
            [
              115.438,
              -8.67861,
              0
            ],
            [
              115.436,
              -8.67931,
              0
            ],
            [
              115.434,
              -8.67736,
              0
            ],
            [
              115.432,
              -8.67839,
              0
            ],
            [
              115.429,
              -8.6799,
              0
            ],
            [
              115.427,
              -8.67989,
              0
            ],
            [
              115.425,
              -8.68175,
              0
            ],
            [
              115.426,
              -8.68508,
              0
            ],
            [
              115.426,
              -8.6875,
              0
            ],
            [
              115.427,
              -8.68974,
              0
            ],
            [
              115.429,
              -8.69077,
              0
            ],
            [
              115.432,
              -8.69101,
              0
            ],
            [
              115.433,
              -8.69284,
              0
            ],
            [
              115.436,
              -8.69295,
              0
            ],
            [
              115.438,
              -8.69272,
              0
            ],
            [
              115.44,
              -8.69272,
              0
            ],
            [
              115.443,
              -8.69248,
              0
            ],
            [
              115.446,
              -8.69184,
              0
            ],
            [
              115.449,
              -8.68994,
              0
            ],
            [
              115.452,
              -8.68695,
              0
            ],
            [
              115.453,
              -8.68522,
              0
            ],
            [
              115.456,
              -8.68211,
              0
            ],
            [
              115.459,
              -8.67962,
              0
            ],
            [
              115.461,
              -8.6779,
              0
            ],
            [
              115.464,
              -8.67392,
              0
            ],
            [
              115.465,
              -8.67156,
              0
            ],
            [
              115.464,
              -8.66915,
              0
            ],
            [
              115.461,
              -8.66834,
              0
            ],
            [
              115.458,
              -8.66898,
              0
            ],
            [
              115.456,
              -8.66985,
              0
            ],
            [
              115.454,
              -8.67008,
              0
            ],
            [
              115.45,
              -8.66951,
              0
            ],
            [
              115.449,
              -8.66646,
              0
            ],
            [
              115.451,
              -8.66444,
              0
            ],
            [
              115.454,
              -8.66239,
              0
            ]
          ]
        ]
      },
      "properties": {
        "name": "J.4",
        "description": "Selat Badung"
      }
    }
  ]
}